{"nodes": [{"id": "pollyfallback_doc", "label": "Polly Fallback Messages", "file_type": "document", "source_file": "packages/skills/polly/references/fallback-messages.md", "source_location": null, "source_url": null, "captured_at": null, "author": null, "contributor": null}, {"id": "pollyfallback_generic", "label": "Skip/Manual/Install Template", "file_type": "concept", "source_file": "packages/skills/polly/references/fallback-messages.md", "source_location": null, "source_url": null, "captured_at": null, "author": null, "contributor": null}], "edges": [{"source": "pollyfallback_doc", "target": "pollyfallback_generic", "relation": "references", "confidence": "EXTRACTED", "confidence_score": 1.0, "source_file": "packages/skills/polly/references/fallback-messages.md", "source_location": null, "weight": 1.0}, {"source": "pollyfallback_doc", "target": "skill_skillfinder", "relation": "references", "confidence": "EXTRACTED", "confidence_score": 1.0, "source_file": "packages/skills/polly/references/fallback-messages.md", "source_location": null, "weight": 1.0}], "hyperedges": []}